lazyimport/__init__.py
lazyimport/_version.py
lazyimport/bzrlib_core.py
lazyimport/errors.py
lazyimport-0.0.4.dist-info/METADATA
lazyimport-0.0.4.dist-info/RECORD
lazyimport-0.0.4.dist-info/WHEEL
lazyimport-0.0.4.dist-info/top_level.txt
tests/__init__.py
tests/test_lazyimport.py
